mihrabai/__init__.py
mihrabai/cli.py
mihrabai/config.py
mihrabai/factory.py
mihrabai/agents/__init__.py
mihrabai/agents/data_agent.py
mihrabai/common/__init__.py
mihrabai/common/interfaces.py
mihrabai/core/__init__.py
mihrabai/core/agent.py
mihrabai/core/chat_agent.py
mihrabai/core/memory.py
mihrabai/core/memory_task_agent.py
mihrabai/core/message.py
mihrabai/core/task_agent.py
mihrabai/core/types.py
mihrabai/docs/advanced_handoff_system.md
mihrabai/docs/handoff_system.md
mihrabai/docs/multi_agent_system.md
mihrabai/docs/documentation/documentation.md
mihrabai/docs/documentation/documentations_models.md
mihrabai/docs/documentation/handoff_documentation.md
mihrabai/docs/documentation/handoff_system_readme.md
mihrabai/docs/documentation/memory_and_multi_provider.md
mihrabai/docs/documentation/tracing_docuemntation.md
mihrabai/docs/documentation/tracing_documentation.md
mihrabai/docs/guide/api_reference.md
mihrabai/docs/guide/creating_custom_tools.md
mihrabai/docs/guide/index.md
mihrabai/docs/guide/quick_start_guide.md
mihrabai/docs/guide/using_groq_provider.md
mihrabai/docs/guide/using_mihrab_with_tools.md
mihrabai/examples/README.md
mihrabai/examples/advanced/README.md
mihrabai/examples/advanced/data_agent_example.py
mihrabai/examples/advanced/handoff_example.py
mihrabai/examples/advanced/improved_handoff_example.py
mihrabai/examples/advanced/memory_and_multi_provider.py
mihrabai/examples/advanced/model_fallback_example.py
mihrabai/examples/advanced/multi_agent_collaboration.py
mihrabai/examples/basic/basic_chat_agent.py
mihrabai/examples/basic/function_calling.py
mihrabai/examples/basic/streaming_chat.py
mihrabai/examples/tools/code_generation_example.py
mihrabai/examples/tools/custom_tools_example.py
mihrabai/examples/tools/filesystem_tools_example.py
mihrabai/examples/tools/web_tools_example.py
mihrabai/handoff/__init__.py
mihrabai/handoff/agent.py
mihrabai/handoff/conditions.py
mihrabai/handoff/config.py
mihrabai/handoff/filters.py
mihrab_ai_agent-0.2.1.dist-info/LICENSE
mihrab_ai_agent-0.2.1.dist-info/METADATA
mihrab_ai_agent-0.2.1.dist-info/WHEEL
mihrab_ai_agent-0.2.1.dist-info/entry_points.txt
mihrab_ai_agent-0.2.1.dist-info/top_level.txt
mihrab_ai_agent-0.2.1.dist-info/RECORD
