Metadata-Version: 2.2
Name: mihrab-ai-agent
Version: 0.2.1
Summary: A flexible framework for building and deploying LLM-powered agents with multiple provider support, inspired by the mihrab that guides prayer in a mosque
Author-email: Ragii Abdullah Shehab <ragi.shehab1@gmail.com>
License: MIT
Project-URL: Homepage, https://github.com/ragishehab/mihrab-ai-agent
Project-URL: Bug Tracker, https://github.com/ragishehab/mihrab-ai-agent/issues
Project-URL: Documentation, https://github.com/ragishehab/mihrab-ai-agent/blob/main/README.md
Keywords: llm,agents,ai,openai,anthropic,groq,framework
Classifier: Development Status :: 4 - Beta
Classifier: Intended Audience :: Developers
Classifier: License :: OSI Approved :: MIT License
Classifier: Programming Language :: Python :: 3
Classifier: Programming Language :: Python :: 3.9
Classifier: Programming Language :: Python :: 3.10
Classifier: Programming Language :: Python :: 3.11
Classifier: Programming Language :: Python :: 3.12
Classifier: Topic :: Scientific/Engineering :: Artificial Intelligence
Classifier: Topic :: Software Development :: Libraries :: Python Modules
Requires-Python: >=3.9
License-File: LICENSE
Requires-Dist: openai>=1.0.0
Requires-Dist: anthropic>=0.7.0
Requires-Dist: groq>=0.4.0
Requires-Dist: tiktoken>=0.5.0
Requires-Dist: aiohttp>=3.9.0
Requires-Dist: asyncio>=3.4.3
Requires-Dist: pydantic>=2.0.0
Requires-Dist: python-dotenv>=1.0.0
Requires-Dist: sympy>=1.12.0
Requires-Dist: pytz>=2023.3
Requires-Dist: numpy>=1.24.0
Requires-Dist: tenacity>=8.2.0
Requires-Dist: colorlog>=6.7.0
Requires-Dist: argparse>=1.4.0
